redis_entraid/__init__.py
redis_entraid/cred_provider.py
redis_entraid/identity_provider.py
redis_entraid-1.0.0.dist-info/licenses/LICENSE
redis_entraid-1.0.0.dist-info/METADATA
redis_entraid-1.0.0.dist-info/WHEEL
redis_entraid-1.0.0.dist-info/top_level.txt
redis_entraid-1.0.0.dist-info/RECORD
