Metadata-Version: 2.4
Name: redis-entraid
Version: 1.0.0
Summary: Entra ID credentials provider implementation for Redis-py client
Author-email: "Redis Inc." <oss@redis.com>
Requires-Python: >=3.8
License-File: LICENSE
Requires-Dist: redis>=5.3.0
Requires-Dist: PyJWT~=2.9.0
Requires-Dist: msal~=1.31.0
Requires-Dist: azure-identity~=1.20.0
Dynamic: license-file
